cdp_parser/__init__.py
cdp_parser/cdp.py
cahier_de_prepa_parser-1.0.2.dist-info/LICENSE
cahier_de_prepa_parser-1.0.2.dist-info/METADATA
cahier_de_prepa_parser-1.0.2.dist-info/WHEEL
cahier_de_prepa_parser-1.0.2.dist-info/top_level.txt
cahier_de_prepa_parser-1.0.2.dist-info/RECORD
