Metadata-Version: 2.1
Name: cahier-de-prepa-parser
Version: 1.0.2
Summary: Python parser pour Cahier de Prépa
Home-page: https://www.github.com/Bapt5/cahier-de-prepa-parser
Download-URL: https://github.com/Bapt5/cahier-de-prepa-parser/archive/refs/tags/v1.0.2.tar.gz
Author: Bapt5
Author-email: drouillet.baptiste@gmail.com
License: MPL2.0
Keywords: cahier de prépa,parser
Requires-Python: >=3.7
License-File: LICENSE
Requires-Dist: requests >=2.21.0
Requires-Dist: beautifulsoup4 >=4.12.0
